{
  "basics": {
    "name": "Jonathan Quemuel,EIT",
    "label": "Student",
    "picture": "https://jonkiote.github.io/images/Jon1.jpg",
    "email": "jkq@hawaii.edu",
    "phone": "808-636-1746",
    "website": "https://Jonkiote.github.io",
    "summary": "I have earned a bachelor's degree in Computer Engineering and have passed the electrical/computer engineering FE exam. I am currently, looking for a job in my field.",
    "location": {
      "address": "1420 Gregory St.",
      "postalCode": "96817",
      "city": "Honolulu",
      "countryCode": "USA",
      "region": "Hawaii"
    },
    "profiles": [
      {
        "network": "github",
        "username": "jonkiote",
        "url": "http://github.com/jonkiote"
      },
      {
        "network": "linkedin",
        "username": "Jonathan Quemuel",
        "url": "https://www.linkedin.com/in/jonathan-quemuel-076a98a5"
      }
    ]
  },
  "interests": [
    {
      "name": "Robotics",
      "keywords": [
      ]
    },
    {
      "name": "Software Engineering",
      "keywords": [
      ]
    },
    {
      "name": "Game Design",
      "keywords": [
      ]
    },
    {
      "name": "Database Management",
      "keywords": [
      ]
    }
  ],
  "skills": [
    {
      "name": "Languages and Frameworks",
      "level": "",
      "keywords": [
        "C",
        "C++",
        "Java",
        "Python",
        "Javascript",
        "Semantic UI",
        "Meteor",
        "VHDL",
        "Verilog",
        "MATLAB",
        "HTML",
        "CSS"
      ]
    },
    {
      "name": "Toolsets/OS",
      "level": "",
      "keywords": [
        "MacOS",
        "Windows",
        "Linux",
        "Ubuntu",
        "CentOS",
        "Git/GitHub",
        "g++",
        "Cmake",
        "IntelliJ",
        "Clion",
        "Eclipse",
        "Vivado"
      ]
    }
  ],
  "education": [
    {
      "institution": "University of Hawaii, Honolulu, HI",
      "area": "Computer Engineering (Fall, 2016)",
      "studyType": "B.S.",
      "startDate": "2013-09-01",
      "endDate": "2016-12-15",
      "courses": [
        "EE 211: Basic Circuit Analysis I",
        "EE 213: Basic Circuit Analysis II",
        "EE 260: Introduction to Digital Design",
        "EE 315: Signals and Systems Analysis",
        "EE 323: Microelectronic Circuits",
        "EE 324: Physical Electronics",
        "EE 342: EE Probability and Statistics",
        "EE 361: Digital System Design",
        "EE 371: Engineering Electromagnetics I",
        "EE 406: Intoduction to Computer Network and Security",
        "EE 449: Computer Communication Networks",
        "EE 468: Introduction to Operating Systems",
        "EE 496: Capstone Design Project",
        "ICS 111: Introduction to Computer Science I",
        "ICS 141: Discrete Mathematics I",
        "ICS 211: Introduction to Computer Science II",
        "ICS 212: Program Structure",
        "ICS 314: Software Engineering I"
      ]
    }
  ],
  "volunteer": [
    {
      "organization": "",
      "website": "",
      "position": "Professional organization involvement",
      "startDate": "",
      "endDate": "",
      "summary": "",
      "highlights": [
        "Member, IEEE Student Branch, 2014-2016",
        "Member, ITMA, 2013",
        "Member, Leo CLub, 2010"
      ]
    }
  ],
  "awards": [
    {
      "title": "Eighth Place",
      "date": "2015",
      "awarder": "University of Hawaii Micromouse Competition",
      "summary": "My team won eighth place in 2015.  See my portfolio site for more details."
    },
    {
      "title": "Dean's List",
      "date": "Fall 2016",
      "awarder": "University of Hawaii at Manoa College of Engineering",
      "summary": "I achieved a semester GPA of 3.5 or higher."
    },
    {
      "title": "Engineer in Training",
      "date": "October 28, 2017",
      "summary": "I took and passed the state FE exam for electrical and computer engineering."
    }
  ],
  "references": [
    {
      "name": "Available upon request",
      "reference": ""
    }
  ]
}
